dbt/__init__.py
dbt/adapters/__init__.py
dbt/adapters/dameng/__init__.py
dbt/adapters/dameng/__version__.py
dbt/adapters/dameng/column.py
dbt/adapters/dameng/connections.py
dbt/adapters/dameng/impl.py
dbt/adapters/dameng/keyword_catalog.py
dbt/adapters/dameng/relation.py
dbt/include/__init__.py
dbt/include/dameng/__init__.py
dbt/include/dameng/dbt_project.yml
dbt/include/dameng/profile_template.yml
dbt/include/dameng/macros/adapters.sql
dbt/include/dameng/macros/apply_grants.sql
dbt/include/dameng/macros/catalog.sql
dbt/include/dameng/macros/columns.sql
dbt/include/dameng/macros/schema_tests.sql
dbt/include/dameng/macros/materializations/incremental/incremental.sql
dbt/include/dameng/macros/materializations/incremental/strategies.sql
dbt/include/dameng/macros/materializations/seed/seed.sql
dbt/include/dameng/macros/materializations/snapshot/snapshot.sql
dbt/include/dameng/macros/materializations/snapshot/snapshot_merge.sql
dbt/include/dameng/macros/materializations/snapshot/strategies.sql
dbt/include/dameng/macros/materializations/table/table.sql
dbt/include/dameng/macros/materializations/tests/helpers.sql
dbt/include/dameng/macros/materializations/view/view.sql
tests/__init__.py
tests/conftest.py
dbt_dameng-1.4.5.dist-info/LICENSE
dbt_dameng-1.4.5.dist-info/METADATA
dbt_dameng-1.4.5.dist-info/WHEEL
dbt_dameng-1.4.5.dist-info/top_level.txt
dbt_dameng-1.4.5.dist-info/RECORD
