Metadata-Version: 2.1
Name: dbt-dameng
Version: 1.4.5
Summary: The dameng adapter plugin for dbt (data build tool)
Home-page: https://github.com/sqlking22/dbt-dameng
Author: sqlking22
License: Apache Software License 2.0
Project-URL: Documentation, https://github.com/sqlking22/dbt-dameng
Project-URL: Source, https://github.com/sqlking22/dbt-dameng
Project-URL: Bug Tracker, https://github.com/sqlking22/dbt-dameng/issues
Project-URL: CI, https://github.com/sqlking22/dbt-dameng/actions
Project-URL: Release Notes, https://github.com/sqlking22/dbt-dameng/releases
Platform: UNKNOWN
Classifier: Development Status :: 5 - Production/Stable
Classifier: Intended Audience :: Developers
Classifier: License :: OSI Approved :: Apache Software License
Classifier: Natural Language :: English
Classifier: Programming Language :: Python :: 3
Classifier: Programming Language :: Python :: 3.7
Classifier: Programming Language :: Python :: 3.8
Classifier: Programming Language :: Python :: 3.9
Classifier: Programming Language :: Python :: 3.10
Classifier: Programming Language :: Python :: 3.11
Requires-Python: >=3.7.0
Requires-Dist: dbt-core (==1.4.5)
Requires-Dist: dmPython (==2.4.5)
